IconFonts-0.0.2.dist-info/top_level.txt
IconFonts-0.0.2.dist-info/RECORD
IconFonts-0.0.2.dist-info/DESCRIPTION.rst
IconFonts-0.0.2.dist-info/WHEEL
IconFonts-0.0.2.dist-info/metadata.json
IconFonts-0.0.2.dist-info/METADATA
iconfonts/__init__.py
iconfonts/utils.py
iconfonts/fonts.py
iconfonts/api.py
iconfonts/django/__init__.py
iconfonts/django/models.py
iconfonts/django/utils.py
iconfonts/django/templatetags/__init__.py
iconfonts/django/templatetags/icons.py
