Metadata-Version: 2.0
Name: IconFonts
Version: 0.0.2
Summary: Your project description goes here
Home-page: https://github.com/joke2k/iconfonts
Author: joke2k
Author-email: joke2k@gmail.com
License: BSD
Keywords: iconfonts
Platform: UNKNOWN
Classifier: Development Status :: 2 - Pre-Alpha
Classifier: Framework :: Django
Classifier: Intended Audience :: Developers
Classifier: License :: OSI Approved :: MIT License
Classifier: Natural Language :: English
Classifier: Programming Language :: Python :: 2
Classifier: Programming Language :: Python :: 2.6
Classifier: Programming Language :: Python :: 2.7
Classifier: Programming Language :: Python :: 3
Classifier: Programming Language :: Python :: 3.3
